fineio/__init__.py
fineio/cpu_detect.py
fineio/executor.py
fineio/shutdown.py
fineio-0.0.1a2.dist-info/licenses/LICENSE
fineio-0.0.1a2.dist-info/METADATA
fineio-0.0.1a2.dist-info/WHEEL
fineio-0.0.1a2.dist-info/top_level.txt
fineio-0.0.1a2.dist-info/RECORD
