Metadata-Version: 2.4
Name: fineio
Version: 0.0.1a2
Summary: FineIO: User-friendly sync/async Python execution
Author-email: Abdulmajid Yunusov <you@example.com>
License: MIT
Project-URL: Homepage, https://github.com/goldendevuz/fineio
Classifier: Programming Language :: Python :: 3
Classifier: License :: OSI Approved :: MIT License
Classifier: Operating System :: OS Independent
Requires-Python: >=3.7
License-File: LICENSE
Dynamic: license-file
